managedtenants/__init__.py
managedtenants/bundles/__init__.py
managedtenants/bundles/addon_bundles.py
managedtenants/bundles/addon_package.py
managedtenants/bundles/binary_deps.py
managedtenants/bundles/bundle.py
managedtenants/bundles/bundle_builder.py
managedtenants/bundles/cli.py
managedtenants/bundles/csv.py
managedtenants/bundles/docker_api.py
managedtenants/bundles/exceptions.py
managedtenants/bundles/imageset.py
managedtenants/bundles/imageset_creator.py
managedtenants/bundles/index_builder.py
managedtenants/bundles/package_builder.py
managedtenants/bundles/quay_api.py
managedtenants/bundles/registry.py
managedtenants/bundles/utils.py
managedtenants/bundles/auth/config.json
managedtenants/bundles/auth/htpasswd
managedtenants/cli/__init__.py
managedtenants/cli/validate_imageset.py
managedtenants/core/__init__.py
managedtenants/core/addon_manager.py
managedtenants/core/runner.py
managedtenants/core/status.py
managedtenants/core/version.py
managedtenants/core/addons_loader/__init__.py
managedtenants/core/addons_loader/addon.py
managedtenants/core/addons_loader/bundle.py
managedtenants/core/addons_loader/exceptions.py
managedtenants/core/addons_loader/manifest.py
managedtenants/core/addons_loader/package.py
managedtenants/core/addons_loader/sss.py
managedtenants/core/tasks_loader/__init__.py
managedtenants/core/tasks_loader/environment.py
managedtenants/core/tasks_loader/exceptions.py
managedtenants/core/tasks_loader/post_task.py
managedtenants/core/tasks_loader/pre_task.py
managedtenants/core/tasks_loader/task.py
managedtenants/data/__init__.py
managedtenants/data/environments.py
managedtenants/data/macros.j2
managedtenants/data/paths.py
managedtenants/data/selectorsyncset.yaml.j2
managedtenants/schemas/__init__.py
managedtenants/schemas/imageset.schema.yaml
managedtenants/schemas/metadata.schema.yaml
managedtenants/schemas/mtbundles.schema.yaml
managedtenants/schemas/shared/addon_parameters.json
managedtenants/schemas/shared/addon_requirements.json
managedtenants_cli-1.50.0.dist-info/LICENSE
managedtenants_cli-1.50.0.dist-info/METADATA
managedtenants_cli-1.50.0.dist-info/WHEEL
managedtenants_cli-1.50.0.dist-info/entry_points.txt
managedtenants_cli-1.50.0.dist-info/top_level.txt
managedtenants_cli-1.50.0.dist-info/RECORD
