Metadata-Version: 2.1
Name: managedtenants_cli
Version: 1.50.0
Summary: A CLI tool commonly used by MT-SRE projects at Red Hat
Home-page: https://github.com/mt-sre/managed-tenants-cli
Author: Red Hat Managed Tenants SRE Team
Author-email: sd-mt-sre@redhat.com
License: Apache-2.0
Classifier: Intended Audience :: Developers
Classifier: License :: OSI Approved :: Apache Software License
Classifier: Natural Language :: English
Classifier: Operating System :: POSIX :: Linux
Classifier: Programming Language :: Python :: 3.9
Classifier: Topic :: Software Development :: Libraries
Requires-Python: >=3.9
License-File: LICENSE
Requires-Dist: Jinja2 <4.0,>=2.10
Requires-Dist: markupsafe ~=2.0.1
Requires-Dist: PyYAML ~=5.4.1
Requires-Dist: jsonschema ~=4.7
Requires-Dist: requests <2.29.0
Requires-Dist: sretoolbox ~=2.4
Requires-Dist: semver ~=2.13.0
Requires-Dist: python-gitlab ~=2.6
Requires-Dist: checksumdir ~=1.2
Requires-Dist: docker ~=5.0.3
Requires-Dist: podman ~=5.0.0
